nupaac/__init__.py
nupaac/nucs.py
nupaac-0.1.7.dist-info/LICENSE
nupaac-0.1.7.dist-info/METADATA
nupaac-0.1.7.dist-info/WHEEL
nupaac-0.1.7.dist-info/RECORD
