Metadata-Version: 2.3
Name: nupaac
Version: 0.1.7
Summary: Pandas Series accessor to handle nuclides.
License: MIT
Keywords: radioactive,nuclides,radionuclides,radio chemistry,nuclear chemistry,physics,health physics,half-life,science,pandas,series
Author: Christian Schreinemachers (Cs137)
Requires-Python: >=3.9
Classifier: Intended Audience :: Education
Classifier: Intended Audience :: Science/Research
Classifier: License :: OSI Approved :: MIT License
Classifier: Programming Language :: Python :: 3
Classifier: Programming Language :: Python :: 3.9
Classifier: Programming Language :: Python :: 3.10
Classifier: Programming Language :: Python :: 3.11
Classifier: Programming Language :: Python :: 3.12
Classifier: Programming Language :: Python :: 3.13
Classifier: Programming Language :: Python :: 3 :: Only
Classifier: Topic :: Education
Classifier: Topic :: Scientific/Engineering
Requires-Dist: numpy (>=2.2.2,<3.0.0)
Requires-Dist: pandas (>=2.2.3,<3.0.0)
Requires-Dist: pint-pandas (>=0.7.1,<0.8.0)
Requires-Dist: radioactivedecay (>=0.6.1,<0.7.0)
Requires-Dist: scipy (>=1.15.1,<2.0.0)
Project-URL: Changelog, https://codeberg.org/Cs137/NuPaAc/src/branch/main/CHANGELOG.md
Project-URL: Issues, https://codeberg.org/Cs137/NuPaAc/issues
Project-URL: Repository, https://codeberg.org/Cs137/NuPaAc
